setup.py
tapioca_bitbucket/__init__.py
tapioca_bitbucket/resource_mapping.py
tapioca_bitbucket/tapioca_bitbucket.py
tapioca_bitbucket.egg-info/PKG-INFO
tapioca_bitbucket.egg-info/SOURCES.txt
tapioca_bitbucket.egg-info/dependency_links.txt
tapioca_bitbucket.egg-info/not-zip-safe
tapioca_bitbucket.egg-info/requires.txt
tapioca_bitbucket.egg-info/top_level.txt