Metadata-Version: 1.1
Name: tapioca-bitbucket
Version: 0.1
Summary: Bitbucket API wrapper using tapioca
Home-page: https://github.com/aericson/tapioca-bitbucket
Author: Andre Ericson
Author-email: de.ericson@gmail.com
License: BSD
Keywords: tapioca-bitbucket
Platform: UNKNOWN
Classifier: Development Status :: 2 - Pre-Alpha
Classifier: Intended Audience :: Developers
Classifier: License :: OSI Approved :: BSD License
Classifier: Natural Language :: English
Classifier: Programming Language :: Python :: 2
Classifier: Programming Language :: Python :: 2.7
